{
  "kashrut": {
    "Kosher_for_Passover_Remark": "",
    "Board_of_Supervision": [71144],
    "Cooking_Israel": [],
    "Kosher_Supervision_Type": [180],
    "Kosher_for_Passover": [6402],
    "Rabbinate": [],
    "Israel_Milk": [],
    "Sheviit_Orlah_Tevel": []
  },
  "full_desc": "",
  "kosher_type": null,
  "features": [],
  "price": { "price": 8.1 },
  "prop": { "unit": null, "sw_shakil": 0, "by_kilo": 0, "by_kilo_content": 0, "status": 2 },
  "id": 328799,
  "multiplication": 1,
  "barcode": 7290111340178,
  "brand": 2060,
  "recipes": [],
  "images": {
    "small": "/product/7290111340178/small.jpg",
    "original": "/product/7290111340178/large.jpg",
    "trim": "/product/7290111340178/trim.jpg",
    "transparent": "/product/7290111340178/transparent.png",
    "gallery": []
  },
  "department_id": 59,
  "exceptionDays": [],
  "preference": [],
  "kashruts": [],
  "available_in": [
    82, 179, 279, 290, 331, 411, 412, 1197, 1198, 1214, 1221, 1225, 1226, 1306, 1307, 1314, 1323,
    1329, 1330, 1332, 1333, 1378, 1389, 1401
  ],
  "gs": {
    "Ingredient_Sequence_and_Name": "מכיל פחות מ-5% חומרים פעילי שטח, משמרים, בושם וחומרי עזר אחרים.",
    "Product_Dimensions": {
      "Product_Gross_Weight": { "UOM": "גרם", "text": "383.4 גרם", "value": "383.4" },
      "Net_Weight": { "UOM": "גרם", "text": "375.2 גרם", "value": "375.2" },
      "Product_Height": { "UOM": "סמ", "text": "5.6 סמ", "value": "5.6" },
      "Price_Comparison_Content": [{ "UOM": null, "text": "יחידה ", "value": "יחידה" }],
      "Product_Width": { "UOM": "סמ", "text": "19.3 סמ", "value": "19.3" },
      "Product_Depth": { "UOM": "סמ", "text": "10.5 סמ", "value": "10.5" }
    },
    "Contains_Sulfur_Dioxide": null,
    "Alcohol_Percentage_in_Product": null,
    "BrandName": "ניקול",
    "Product_Description_English": "NIKOL SOFTENER MULTI PURPOSE WET יחידות",
    "Country_of_Origin": "IL",
    "Fat_Percentage_in_Product": null,
    "Allergen_Type_Code_and_Containment_May_Contain": [],
    "pH": null,
    "Serving_Size_Description": "",
    "litzman": false,
    "Food_Symbol_Red": [{ "code": "FSR1", "value": "ללא סימון" }],
    "Allergen_Type_Code_and_Containment": [],
    "Color_Number": null,
    "Search_Tags": [
      "7290111340178",
      "ניקול",
      "מטליות",
      "לחות",
      "לניקוי כללי",
      "50 יחידות",
      "בניחוח מרכך כביסה",
      "ניקוי",
      "ניקיון",
      "",
      "מרכך כביסה",
      "דוחה אבק",
      "מטליות לחות",
      "חד פעמי",
      "כללי",
      "SOFTENER",
      "MULTI PURPOSE CLOTH",
      "wet יחידות",
      "cleaning"
    ],
    "internal_product_description": "ניקול מטליות לחות לניקוי כללי בניחוח מרכך כביסה 50 יחידות",
    "Color": null,
    "Diet_Information": [],
    "Nutritional_Values": [],
    "Fruit_Percentage_in_Product": null,
    "Serving_Suggestion": "להעביר את המטלית על גבי המשטח. לאחר השימוש יש להקפיד לסגור את המכסה למניעת התייבשות המטליות. ליעילות מקסימלית יש להשתמש על גבי משטח יבש.",
    "Forbidden_Under_the_Age_of_18": null,
    "name": "ניקול מטליות לחות לניקוי כללי בניחוח מרכך כביסה,  בתוספת פורמולה דוחה אבק', 50 יחידות",
    "Hazard_Precautionary_Statement": "לא למאכל. לשימוש חיצוני בלבד. יש להרחיק מהישג ידם של ילדים וחיות מחמד. לא לשימוש\nלצרכי היגיינה אישית. אין להשליך לאסלה. יש לשטוף ידיים לאחר השימוש. יש להשתמש במוצר רק למטרה לשמה הוא נועד. יש להימנע ממגע בעיניים ועור פגוע. במקרה של מגע יש לשטוף היטב במים. במידה והגירוי ממשיך יש להתייעץ עם רופא. יש לנסות ראשית באזור מוסתר מוגבל בכדי לבחון התאמה למשטח. יש להשתמש במשטח יבש. יש להישמע להוראות הניקוי של יצרן המשטח.",
    "short_name": "מטליות לחות לניקוי כללי בניחוח מרכך כביסה",
    "Consumer_Storage_Instructions": "",
    "Net_Content": { "UOM": "יחידות", "text": "50 יחידות", "value": "50" },
    "Healthy_Product": "",
    "Cream_Percentage_in_Product": null
  },
  "sale": [],
  "mainImage": 1,
  "group_id": 248,
  "name": "מטליות לחות לניקוי 50 יח ניקול",
  "site_id": 1,
  "sub_group_id": 204,
  "short_desc": "",
  "lables": [],
  "properties": [],
  "is360": 1,
  "has_coupon": false
}
