{
  "kashrut": {
    "Kosher_for_Passover_Remark": "",
    "Board_of_Supervision": [],
    "Cooking_Israel": [],
    "Kosher_Supervision_Type": [180],
    "Kosher_for_Passover": [],
    "Rabbinate": [],
    "Israel_Milk": [],
    "Sheviit_Orlah_Tevel": []
  },
  "full_desc": "",
  "kosher_type": null,
  "features": [],
  "price": { "price": 11.7 },
  "prop": { "unit": null, "sw_shakil": 0, "by_kilo": 0, "by_kilo_content": 0, "status": 2 },
  "id": 335633,
  "multiplication": 1,
  "barcode": 8690784516440,
  "brand": 1234,
  "recipes": [],
  "images": {
    "small": "/product/8690784516440/small.jpg",
    "original": "/product/8690784516440/large.jpg",
    "trim": "/product/8690784516440/trim.jpg",
    "transparent": "/product/8690784516440/transparent.png",
    "gallery": []
  },
  "department_id": 59,
  "exceptionDays": [],
  "preference": [],
  "kashruts": [],
  "available_in": [
    82, 179, 279, 306, 331, 411, 412, 1197, 1198, 1214, 1221, 1226, 1306, 1307, 1314, 1332, 1378,
    1389, 1401
  ],
  "gs": {
    "Ingredient_Sequence_and_Name": "מכיל:\nAlcohols, C13-15-branched and linear, ethoxylated, EO=8, Formic acid, quaternary ammonium, compounds, benzyl-C12-18 - alkyldimethyl, chlorides\n\nחומרים פעילים:\nQuaternary ammonium compounds, benzyl- C12-18-alkyldimethyl, chlorides, 0.1828% (0.1828g/100g) \nQuaternary ammonium compounds, di-C8-10-alkyldimethyl, chkorides 0.2742% (0.2742g/100g)",
    "Product_Dimensions": {
      "Product_Gross_Weight": { "UOM": "קג", "text": "0.7 קג", "value": "0.7" },
      "Net_Weight": { "UOM": "גרם", "text": "750 גרם", "value": "750" },
      "Product_Height": { "UOM": "סמ", "text": "28.702 סמ", "value": "28.702" },
      "Price_Comparison_Content": { "UOM": "גרם", "text": "100 גרם", "value": "100" },
      "Product_Width": { "UOM": "סמ", "text": "19.05 סמ", "value": "19.05" },
      "Product_Depth": { "UOM": "סמ", "text": "38.862 סמ", "value": "38.862" }
    },
    "Contains_Sulfur_Dioxide": null,
    "Alcohol_Percentage_in_Product": null,
    "BrandName": "דאק",
    "Product_Description_English": "",
    "Country_of_Origin": "NL",
    "Fat_Percentage_in_Product": null,
    "Allergen_Type_Code_and_Containment_May_Contain": [6843],
    "pH": null,
    "Serving_Size_Description": "",
    "litzman": false,
    "Food_Symbol_Red": [{ "code": "FSR1", "value": "ללא סימון" }],
    "Allergen_Type_Code_and_Containment": [6843],
    "Color_Number": null,
    "Search_Tags": ["8690784516440", "צוואר", "בקבוק", "ייחודי", "כיסוי מקסימלי", "ניקוי יעיל"],
    "internal_product_description": "Duck - משמיד 99.9% חיידקים",
    "Color": null,
    "Diet_Information": [],
    "Nutritional_Values": [],
    "Fruit_Percentage_in_Product": null,
    "Serving_Suggestion": "הוראות שימוש:\n1. יש להרים את מכסה האסלה.\n2. לפתיחת המכסה יש ללחוץ בשני צדיו ולסובבץ\n3. יש להטוות את הבקבוק למילוי צוואר הבקבוק בנוזל ניקוי.\n4. יש להתיז את הנוזל מתחת לדופן האסלה באופן שווה לכיסוי מלא של האסלה\n5. לשפשף במברשת את האסלה מתחת ומעל לקו המים.\n6. יש לסגור את המכסה היטב.\n",
    "Forbidden_Under_the_Age_of_18": null,
    "name": "דאק נוזל לניקוי אסלות בניחוח לבנדר 750 מל",
    "Hazard_Precautionary_Statement": "אם נדרש ייעוץ רפואי.שמור את מכל המוצר או את התווית שלו בהישג יד.\nהרחק מהישג ידם של ילדים אם אתה חש ברע ,פנה למכון הארצי למידע בהרעלות של משרד הבריאות בקרית הרפואית רמב\"ם , או לרופא.\nבזהירות במים במשך דקות אחדות. הסר עדשות מגע, אם ישנן, ואם ניתן להסירן בנקל. המשך לשטוף. לבש משקפי מגן. מיועד לשימוש בניקוי אסלות בלבד. אין לערבב עם אקנומיקה או חומרי ניקוי אחרים.\nסכנה. לא למאכל.",
    "short_name": "דאק נוזל ג'ל לבנדר",
    "Consumer_Storage_Instructions": "אחסן במקום מוצל",
    "Net_Content": { "UOM": "מל", "text": "750 מל", "value": "750" },
    "Healthy_Product": "",
    "Cream_Percentage_in_Product": null
  },
  "sale": [
    {
      "code": 910364346,
      "sw_kefel": 1,
      "k_cmt": null,
      "deleted_by": "RL",
      "k_acz_dis": 8,
      "active": 1,
      "created_at": "2025-08-10T12:52:00.000000Z",
      "cmt": 1,
      "label": "5% הנחה על מגוון מוצרים\n1 ב NaN ₪",
      "type": 1,
      "is_wallet": 0,
      "deleted_at": null,
      "is_personal": 1,
      "updated_at": "2026-01-08T08:58:53.000000Z",
      "approved_at": "2026-01-08 10:58:53",
      "name": "8% הנחה על מגוון מוצרים",
      "k_scm": null,
      "from": "2025-08-10 00:00:00",
      "id": 723012,
      "to": "2026-06-26 23:59:59",
      "scm": null,
      "pending_approval": 0,
      "is_club": 0
    }
  ],
  "mainImage": 1,
  "group_id": 245,
  "name": "דאק ג'ל לניקוי מתקדם בניחוח לבנדר 750מ\"ל",
  "site_id": 1,
  "sub_group_id": 62,
  "short_desc": "",
  "lables": [],
  "properties": [],
  "is360": 1,
  "has_coupon": true
}
