{
  "kashrut": {
    "Kosher_for_Passover_Remark": "",
    "Board_of_Supervision": [],
    "Cooking_Israel": [0],
    "Kosher_Supervision_Type": [183],
    "Kosher_for_Passover": [6402],
    "Rabbinate": [67267, 67016, 67011],
    "Israel_Milk": [],
    "Sheviit_Orlah_Tevel": [0]
  },
  "full_desc": "",
  "kosher_type": null,
  "features": [],
  "price": { "price": 19.6 },
  "prop": { "unit": 0, "sw_shakil": 0, "by_kilo": 0, "by_kilo_content": 0, "status": 2 },
  "id": 405225,
  "multiplication": 1,
  "barcode": 7290019302452,
  "brand": 1091,
  "recipes": [],
  "images": {
    "small": "/product/7290019302452/small.jpg",
    "original": "/product/7290019302452/large.jpg",
    "trim": "/product/7290019302452/trim.jpg",
    "transparent": null,
    "gallery": []
  },
  "department_id": 57,
  "exceptionDays": [],
  "preference": [],
  "kashruts": [16, 15],
  "available_in": [82, 331, 1314, 1401],
  "gs": {
    "Ingredient_Sequence_and_Name": "מכיל: משמרים (דו-תחמוצת הגופרית,חומצה סורבית)",
    "Product_Dimensions": {
      "Product_Gross_Weight": { "UOM": "גרם", "text": "740 גרם", "value": "740" },
      "Product_Height": { "UOM": "סמ", "text": "25 סמ", "value": "25" },
      "Price_Comparison_Content": { "UOM": "מל", "text": "100 מל", "value": "100" },
      "Product_Width": { "UOM": "סמ", "text": "6 סמ", "value": "6" },
      "Product_Depth": { "UOM": "סמ", "text": "6 סמ", "value": "6" }
    },
    "Contains_Sulfur_Dioxide": null,
    "Alcohol_Percentage_in_Product": "12%",
    "BrandName": "יקבי כרמל",
    "Product_Description_English": "Carmel Private Collection Emerald Riesling Colombard",
    "Country_of_Origin": "IL",
    "Fat_Percentage_in_Product": null,
    "Allergen_Type_Code_and_Containment_May_Contain": [],
    "pH": null,
    "Serving_Size_Description": "",
    "litzman": "",
    "Food_Symbol_Red": [{ "code": "FSR1", "value": "ללא סימון" }],
    "Allergen_Type_Code_and_Containment": [6822],
    "Color_Number": null,
    "Search_Tags": [
      "7290019302452",
      "יין",
      "לבן",
      "פרייבט",
      "קולקשן",
      "אמרלנד",
      "ריזלינג",
      "קולומברד",
      "יקבי כרמל",
      "375 מל"
    ],
    "internal_product_description": "יין לבן פרייבט קולקשן אמרלנד ריזלינג קולומברד  375 מל",
    "Color": null,
    "Diet_Information": [5521],
    "Nutritional_Values": [
      {
        "code": "79001",
        "label": "אנרגיה (קלוריות)",
        "fields": [
          {
            "col_code": "78003",
            "field_id": "5816",
            "col_field_id": "6066",
            "UOM": "קלוריות",
            "col_label": "ל-100 מל",
            "text": "73 קלוריות",
            "value": "73",
            "field_name": "Energy_per_100_grams"
          }
        ]
      }
    ],
    "Fruit_Percentage_in_Product": null,
    "Serving_Suggestion": "טמפרטורת הגשה : 10 מעלות , מומלץ לקרר שעתיים לפני ההגשה .",
    "Forbidden_Under_the_Age_of_18": true,
    "name": "יין לבן פרייבט קולקשן אמרלנד ריזלינג קולומברד  375 מל",
    "Hazard_Precautionary_Statement": "מכיל אלכוהול- מומלץ להימנע משתייה מופרזת",
    "short_name": "יין לבן אמרלנד ריזלינג ",
    "Consumer_Storage_Instructions": "יש לאחסן את היין במקום קריר ואפל.",
    "Net_Content": { "UOM": "מל", "text": "375 מל", "value": "375" },
    "Healthy_Product": "",
    "Cream_Percentage_in_Product": null
  },
  "sale": [
    {
      "code": 910364346,
      "sw_kefel": 1,
      "k_cmt": null,
      "deleted_by": "RL",
      "k_acz_dis": 8,
      "active": 1,
      "created_at": "2025-08-10T12:52:00.000000Z",
      "cmt": 1,
      "label": "5% הנחה על מגוון מוצרים\n1 ב NaN ₪",
      "type": 1,
      "is_wallet": 0,
      "deleted_at": null,
      "is_personal": 1,
      "updated_at": "2026-01-08T08:58:53.000000Z",
      "approved_at": "2026-01-08 10:58:53",
      "name": "8% הנחה על מגוון מוצרים",
      "k_scm": null,
      "from": "2025-08-10 00:00:00",
      "id": 723012,
      "to": "2026-06-26 23:59:59",
      "scm": null,
      "pending_approval": 0,
      "is_club": 0
    }
  ],
  "mainImage": 1,
  "group_id": 239,
  "name": "אמרלד ריזלינג פ.סי 375 מל",
  "site_id": 1,
  "sub_group_id": 34,
  "short_desc": "",
  "lables": [],
  "properties": [],
  "is360": 1,
  "has_coupon": true
}
